ymlstash/__init__.py
ymlstash/stash.py
ymlstash-1.2.1.dist-info/LICENSE
ymlstash-1.2.1.dist-info/METADATA
ymlstash-1.2.1.dist-info/WHEEL
ymlstash-1.2.1.dist-info/RECORD
