Metadata-Version: 2.1
Name: ymlstash
Version: 1.2.1
Summary: A simple ORM-like utility for operating on local YAML files via Python dataclasses
Home-page: https://github.com/yuvadm/ymlstash
License: MIT
Author: Yuval Adam
Author-email: _@yuv.al
Requires-Python: >=3.8,<4.0
Classifier: License :: OSI Approved :: MIT License
Classifier: Programming Language :: Python :: 3
Classifier: Programming Language :: Python :: 3.8
Classifier: Programming Language :: Python :: 3.9
Classifier: Programming Language :: Python :: 3.10
Classifier: Programming Language :: Python :: 3.11
Classifier: Programming Language :: Python :: 3.12
Requires-Dist: pyyaml (>=6.0.1,<7.0.0)
Project-URL: Repository, https://github.com/yuvadm/ymlstash
